[
    {
        "id": 285,
        "image_id": 18,
        "img_name": "Image_18.png",
        "categry_id": 1,
        "category": "bottle",
        "bbox": [
            429,
            212,
            469,
            320
        ]
    },
    {
        "id": 286,
        "image_id": 18,
        "img_name": "Image_18.png",
        "categry_id": 1,
        "category": "bottle",
        "bbox": [
            460,
            196,
            513,
            336
        ]
    },
    {
        "id": 287,
        "image_id": 18,
        "img_name": "Image_18.png",
        "categry_id": 1,
        "category": "bottle",
        "bbox": [
            274,
            224,
            336,
            382
        ]
    },
    {
        "id": 288,
        "image_id": 18,
        "img_name": "Image_18.png",
        "categry_id": 1,
        "category": "bottle",
        "bbox": [
            248,
            187,
            317,
            379
        ]
    },
    {
        "id": 289,
        "image_id": 18,
        "img_name": "Image_18.png",
        "categry_id": 1,
        "category": "bottle",
        "bbox": [
            367,
            175,
            424,
            337
        ]
    },
    {
        "id": 290,
        "image_id": 18,
        "img_name": "Image_18.png",
        "categry_id": 1,
        "category": "bottle",
        "bbox": [
            285,
            189,
            356,
            342
        ]
    },
    {
        "id": 291,
        "image_id": 18,
        "img_name": "Image_18.png",
        "categry_id": 1,
        "category": "bottle",
        "bbox": [
            162,
            205,
            241,
            370
        ]
    },
    {
        "id": 292,
        "image_id": 18,
        "img_name": "Image_18.png",
        "categry_id": 2,
        "category": "can",
        "bbox": [
            341,
            263,
            389,
            357
        ]
    },
    {
        "id": 293,
        "image_id": 18,
        "img_name": "Image_18.png",
        "categry_id": 2,
        "category": "can",
        "bbox": [
            382,
            259,
            432,
            356
        ]
    },
    {
        "id": 294,
        "image_id": 18,
        "img_name": "Image_18.png",
        "categry_id": 2,
        "category": "can",
        "bbox": [
            439,
            251,
            481,
            320
        ]
    },
    {
        "id": 295,
        "image_id": 18,
        "img_name": "Image_18.png",
        "categry_id": 2,
        "category": "can",
        "bbox": [
            242,
            286,
            289,
            364
        ]
    },
    {
        "id": 296,
        "image_id": 18,
        "img_name": "Image_18.png",
        "categry_id": 2,
        "category": "can",
        "bbox": [
            206,
            294,
            245,
            355
        ]
    },
    {
        "id": 297,
        "image_id": 18,
        "img_name": "Image_18.png",
        "categry_id": 2,
        "category": "can",
        "bbox": [
            398,
            249,
            436,
            331
        ]
    },
    {
        "id": 298,
        "image_id": 18,
        "img_name": "Image_18.png",
        "categry_id": 2,
        "category": "can",
        "bbox": [
            475,
            239,
            514,
            324
        ]
    },
    {
        "id": 299,
        "image_id": 18,
        "img_name": "Image_18.png",
        "categry_id": 2,
        "category": "can",
        "bbox": [
            450,
            225,
            495,
            319
        ]
    },
    {
        "id": 300,
        "image_id": 18,
        "img_name": "Image_18.png",
        "categry_id": 2,
        "category": "can",
        "bbox": [
            401,
            236,
            451,
            341
        ]
    }
]