[
    {
        "id": 521,
        "image_id": 34,
        "img_name": "Image_34.png",
        "categry_id": 1,
        "category": "bottle",
        "bbox": [
            244,
            186,
            309,
            345
        ]
    },
    {
        "id": 522,
        "image_id": 34,
        "img_name": "Image_34.png",
        "categry_id": 1,
        "category": "bottle",
        "bbox": [
            396,
            161,
            458,
            322
        ]
    },
    {
        "id": 523,
        "image_id": 34,
        "img_name": "Image_34.png",
        "categry_id": 1,
        "category": "bottle",
        "bbox": [
            293,
            252,
            377,
            408
        ]
    },
    {
        "id": 524,
        "image_id": 34,
        "img_name": "Image_34.png",
        "categry_id": 1,
        "category": "bottle",
        "bbox": [
            63,
            275,
            134,
            398
        ]
    },
    {
        "id": 525,
        "image_id": 34,
        "img_name": "Image_34.png",
        "categry_id": 1,
        "category": "bottle",
        "bbox": [
            256,
            144,
            324,
            331
        ]
    },
    {
        "id": 526,
        "image_id": 34,
        "img_name": "Image_34.png",
        "categry_id": 1,
        "category": "bottle",
        "bbox": [
            237,
            146,
            308,
            338
        ]
    },
    {
        "id": 527,
        "image_id": 34,
        "img_name": "Image_34.png",
        "categry_id": 1,
        "category": "bottle",
        "bbox": [
            408,
            103,
            516,
            355
        ]
    },
    {
        "id": 528,
        "image_id": 34,
        "img_name": "Image_34.png",
        "categry_id": 1,
        "category": "bottle",
        "bbox": [
            447,
            92,
            561,
            360
        ]
    },
    {
        "id": 529,
        "image_id": 34,
        "img_name": "Image_34.png",
        "categry_id": 2,
        "category": "can",
        "bbox": [
            306,
            226,
            356,
            320
        ]
    },
    {
        "id": 530,
        "image_id": 34,
        "img_name": "Image_34.png",
        "categry_id": 2,
        "category": "can",
        "bbox": [
            196,
            263,
            271,
            403
        ]
    },
    {
        "id": 531,
        "image_id": 34,
        "img_name": "Image_34.png",
        "categry_id": 2,
        "category": "can",
        "bbox": [
            98,
            285,
            163,
            387
        ]
    },
    {
        "id": 532,
        "image_id": 34,
        "img_name": "Image_34.png",
        "categry_id": 2,
        "category": "can",
        "bbox": [
            387,
            257,
            466,
            387
        ]
    },
    {
        "id": 533,
        "image_id": 34,
        "img_name": "Image_34.png",
        "categry_id": 2,
        "category": "can",
        "bbox": [
            438,
            271,
            513,
            392
        ]
    },
    {
        "id": 534,
        "image_id": 34,
        "img_name": "Image_34.png",
        "categry_id": 2,
        "category": "can",
        "bbox": [
            512,
            211,
            573,
            341
        ]
    },
    {
        "id": 535,
        "image_id": 34,
        "img_name": "Image_34.png",
        "categry_id": 2,
        "category": "can",
        "bbox": [
            444,
            199,
            521,
            358
        ]
    },
    {
        "id": 536,
        "image_id": 34,
        "img_name": "Image_34.png",
        "categry_id": 2,
        "category": "can",
        "bbox": [
            313,
            219,
            390,
            373
        ]
    }
]